{
  "file_path": "/Volumes/My Passport/Ojo otra vez musica de Tidal Original descarga/Consolidado2025/Tracks/Aleks Syntek - Tu Necesitas (Remastered).flac",
  "timestamp": "2025-08-16T22:22:59.130896",
  "metadata": {
    "file_path": "/Volumes/My Passport/Ojo otra vez musica de Tidal Original descarga/Consolidado2025/Tracks/Aleks Syntek - Tu Necesitas (Remastered).flac",
    "file_name": "Aleks Syntek - Tu Necesitas (Remastered).flac",
    "file_size_mb": 38.36,
    "format": ".flac",
    "title": "Tu Necesitas (Remastered)",
    "artist": "Aleks Syntek",
    "album": "12 Favoritas",
    "date": "2014",
    "genre": "Pop",
    "track_number": null,
    "album_artist": null,
    "bpm": 107.0,
    "key": "5B",
    "energy": 7.0,
    "isrc": "MXF060800615",
    "lyrics": null,
    "composer": null,
    "publisher": null,
    "copyright": null,
    "comment": "5B - Energy 7",
    "has_cover": true,
    "cover_format": "image/jpeg",
    "cover_size_kb": 75.46,
    "duration_seconds": 300.65,
    "bitrate": 1067340,
    "sample_rate": 44100,
    "channels": 2,
    "codec": null,
    "energy_scale": "MIK"
  }
}