{
    "file_path": "/Volumes/My Passport/Ojo otra vez musica de Tidal Original descarga/Consolidado2025/Tracks/Babasónicos - Viva Satana.flac",
    "timestamp": "2025-08-16T22:23:04.281040",
    "metadata": {
        "file_path": "/Volumes/My Passport/Ojo otra vez musica de Tidal Original descarga/Consolidado2025/Tracks/Babasónicos - Viva Satana.flac",
        "file_name": "Babasónicos - Viva Satana.flac",
        "file_size_mb": 27.03,
        "format": ".flac",
        "title": "Viva Satana",
        "artist": "Babasónicos",
        "album": "Dopadromo",
        "date": "1996",
        "genre": null,
        "track_number": null,
        "album_artist": null,
        "bpm": 152.0,
        "key": "11A",
        "energy": 7.0,
        "isrc": "ARF109600079",
        "lyrics": null,
        "composer": null,
        "publisher": null,
        "copyright": null,
        "comment": "11A - Energy 7",
        "has_cover": true,
        "cover_format": "image/jpeg",
        "cover_size_kb": 68.68,
        "duration_seconds": 231.39,
        "bitrate": 976112,
        "sample_rate": 44100,
        "channels": 2,
        "codec": null,
        "energy_scale": "MIK"
    }
}
