{
    "file_path": "/Volumes/My Passport/Ojo otra vez musica de Tidal Original descarga/Consolidado2025/Tracks/Billy Ocean - Loverboy (Extended Mix).flac",
    "timestamp": "2025-08-16T22:23:12.305172",
    "metadata": {
        "file_path": "/Volumes/My Passport/Ojo otra vez musica de Tidal Original descarga/Consolidado2025/Tracks/Billy Ocean - Loverboy (Extended Mix).flac",
        "file_name": "Billy Ocean - Loverboy (Extended Mix).flac",
        "file_size_mb": 60.61,
        "format": ".flac",
        "title": "Loverboy (Extended Mix)",
        "artist": "Billy Ocean",
        "album": "Suddenly (Expanded Edition)",
        "date": "1984-09-12",
        "genre": null,
        "track_number": "13",
        "album_artist": "Billy Ocean",
        "bpm": 108.0,
        "key": "11A",
        "energy": 7.0,
        "isrc": "GBAHK0300183",
        "lyrics": "[01:12.30] I don't know what you've got\n[01:16.55] But it plays with my emotions\n[01:17.74] I want you so much\n[01:20.95] Darling, I want to hold you near\n[01:25.57] Want to whisper sweet and tender in your ear\n[01:29.37] Can't stand the thought of you with somebody else\n[01:33.84] Got to have your love, got to have it all to myself\n[01:38.67] I say yeah, yeah, yeah, yeah\n[01:44.17] I wanna be your lover, lover, hmm\n[01:47.78] Wanna be your lover, lover, loverboy\n[01:55.33] Lover, lover, yeah\n[01:58.43] Wanna be your lover, lover, loverboy\n[02:05.17] \n[02:12.38] I'm too far gone, it's hard to stop\n[02:16.76] Baby, you're my dream in motion\n[02:19.02] And I won't give up\n[02:21.57] Teasing me with your fire\n[02:24.52] My finger's on the trigger, you're the one I desire\n[02:29.66] 'Cause I get this feeling, feeling from nobody else\n[02:34.10] Gotta have your tenderness all to myself\n[02:38.87] I say yeah, yeah, yeah, yeah\n[02:45.33] Wanna be your lover, lover, hmm\n[02:49.76] Wanna be your lover, lover, loverboy\n[02:55.56] Lover, lover, yeah\n[02:58.61] Wanna be your lover, lover, oh, oh, yeah\n[03:07.33] \n[03:41.09] And I want you really\n[03:42.63] But the thing is there's nothing I can say\n[03:45.52] To stop you, darling, from running, running away\n[03:50.27] Won't you stay, stay, stay?\n[03:56.22] I wanna be your lover, lover, yeah\n[04:00.73] I wanna be your lover, lover\n[04:06.24] I wanna be your love\n[04:12.63] I gotta be your love\n[04:16.30] I wanna be your love\n[07:06.49] And I can't stand it baby, uh\n[07:10.19] Uh, uh, uh, uh, uh\n[07:16.66] Girl, I love you\n[07:19.80] \n[07:24.56] Uh, and I wanna be your lover\n[08:08.13] ",
        "composer": null,
        "publisher": null,
        "copyright": "(P) 1984 Zomba Records Limited",
        "comment": "11A - Energy 7",
        "has_cover": true,
        "cover_format": "image/jpeg",
        "cover_size_kb": 71.97,
        "duration_seconds": 488.15,
        "bitrate": 1039278,
        "sample_rate": 44100,
        "channels": 2,
        "codec": null,
        "energy_scale": "MIK"
    }
}
