{
    "file_path": "/Volumes/My Passport/Ojo otra vez musica de Tidal Original descarga/Consolidado2025/Tracks/Block & Crown, Marc Rousso - Watchin' Me.flac",
    "timestamp": "2025-08-16T22:23:18.859932",
    "metadata": {
        "file_path": "/Volumes/My Passport/Ojo otra vez musica de Tidal Original descarga/Consolidado2025/Tracks/Block & Crown, Marc Rousso - Watchin' Me.flac",
        "file_name": "Block & Crown, Marc Rousso - Watchin' Me.flac",
        "file_size_mb": 35.63,
        "format": ".flac",
        "title": "Watchin' Me",
        "artist": "Block & Crown, Marc Rousso",
        "album": "Tactical Best Of 2020",
        "date": "2020",
        "genre": "Progressive Trance",
        "track_number": null,
        "album_artist": null,
        "bpm": 126.0,
        "key": "12A",
        "energy": 7.0,
        "isrc": "DEPR32004488",
        "lyrics": null,
        "composer": null,
        "publisher": null,
        "copyright": null,
        "comment": "12A - Energy 7",
        "has_cover": true,
        "cover_format": "image/jpeg",
        "cover_size_kb": 81.3,
        "duration_seconds": 262.86,
        "bitrate": 1133984,
        "sample_rate": 44100,
        "channels": 2,
        "codec": null,
        "energy_scale": "MIK"
    }
}
