{
    "file_path": "/Volumes/My Passport/Ojo otra vez musica de Tidal Original descarga/Consolidado2025/Tracks/Block & Crown - Dirty Dancer.flac",
    "timestamp": "2025-08-16T22:23:15.485396",
    "metadata": {
        "file_path": "/Volumes/My Passport/Ojo otra vez musica de Tidal Original descarga/Consolidado2025/Tracks/Block & Crown - Dirty Dancer.flac",
        "file_name": "Block & Crown - Dirty Dancer.flac",
        "file_size_mb": 35.28,
        "format": ".flac",
        "title": "Dirty Dancer",
        "artist": "Block & Crown",
        "album": "Dirty Dancer",
        "date": "2021",
        "genre": "Tech House",
        "track_number": null,
        "album_artist": null,
        "bpm": 124.0,
        "key": "12B",
        "energy": 7.0,
        "isrc": "QZNFJ2118140",
        "lyrics": null,
        "composer": null,
        "publisher": null,
        "copyright": null,
        "comment": "12B - Energy 7",
        "has_cover": true,
        "cover_format": "image/jpeg",
        "cover_size_kb": 116.87,
        "duration_seconds": 268.06,
        "bitrate": 1099517,
        "sample_rate": 44100,
        "channels": 2,
        "codec": null,
        "energy_scale": "MIK"
    }
}
