{
    "file_path": "/Volumes/My Passport/Ojo otra vez musica de Tidal Original descarga/Consolidado2025/Tracks/Calvin Harris, Rihanna - This Is What You Came For.flac",
    "timestamp": "2025-08-16T22:23:24.543565",
    "metadata": {
        "file_path": "/Volumes/My Passport/Ojo otra vez musica de Tidal Original descarga/Consolidado2025/Tracks/Calvin Harris, Rihanna - This Is What You Came For.flac",
        "file_name": "Calvin Harris, Rihanna - This Is What You Came For.flac",
        "file_size_mb": 47.02,
        "format": ".flac",
        "title": "This Is What You Came For",
        "artist": "Calvin Harris, Rihanna",
        "album": "This Is What You Came For",
        "date": "2016",
        "genre": "Progressive Trance",
        "track_number": null,
        "album_artist": null,
        "bpm": 124.0,
        "key": "8A",
        "energy": 8.0,
        "isrc": "GBARL1600460",
        "lyrics": null,
        "composer": null,
        "publisher": null,
        "copyright": null,
        "comment": "8A - Energy 8",
        "has_cover": true,
        "cover_format": "image/jpeg",
        "cover_size_kb": 101.64,
        "duration_seconds": 221.9,
        "bitrate": 1773163,
        "sample_rate": 44100,
        "channels": 2,
        "codec": null,
        "energy_scale": "MIK"
    }
}
