{
    "file_path": "/Volumes/My Passport/Ojo otra vez musica de Tidal Original descarga/Consolidado2025/Tracks/Ciara - 1, 2 Step (feat. Missy Elliott).flac",
    "timestamp": "2025-08-16T22:23:29.346762",
    "metadata": {
        "file_path": "/Volumes/My Passport/Ojo otra vez musica de Tidal Original descarga/Consolidado2025/Tracks/Ciara - 1, 2 Step (feat. Missy Elliott).flac",
        "file_name": "Ciara - 1, 2 Step (feat. Missy Elliott).flac",
        "file_size_mb": 21.54,
        "format": ".flac",
        "title": "1, 2 Step (feat. Missy Elliott)",
        "artist": "Ciara",
        "album": "Goodies",
        "date": "2004",
        "genre": "Electro House",
        "track_number": null,
        "album_artist": null,
        "bpm": 113.0,
        "key": "6A",
        "energy": 5.0,
        "isrc": "USLF20400121",
        "lyrics": null,
        "composer": null,
        "publisher": null,
        "copyright": null,
        "comment": "6A - Energy 5",
        "has_cover": true,
        "cover_format": "image/jpeg",
        "cover_size_kb": 83.67,
        "duration_seconds": 203.79,
        "bitrate": 882818,
        "sample_rate": 44100,
        "channels": 2,
        "codec": null,
        "energy_scale": "MIK"
    }
}
