{
    "file_path": "/Volumes/My Passport/Ojo otra vez musica de Tidal Original descarga/Consolidado2025/Tracks/Club Nouveau - Rumors.flac",
    "timestamp": "2025-08-16T22:23:29.859904",
    "metadata": {
        "file_path": "/Volumes/My Passport/Ojo otra vez musica de Tidal Original descarga/Consolidado2025/Tracks/Club Nouveau - Rumors.flac",
        "file_name": "Club Nouveau - Rumors.flac",
        "file_size_mb": 31.51,
        "format": ".flac",
        "title": "Rumors",
        "artist": "Club Nouveau",
        "album": "The Collection, Vol. 1",
        "date": "1998-08-18",
        "genre": null,
        "track_number": "1",
        "album_artist": "Club Nouveau",
        "bpm": 106.0,
        "key": "5A",
        "energy": 6.0,
        "isrc": "USLE19827601",
        "lyrics": "[00:29.95] How do rumors get started?\n[00:32.00] They're started by the jealous people and they get mad\n[00:35.32] Seeing something they had and somebody else is holding\n[00:38.82] They tell me that temptation is very hard to resist\n[00:43.65] But these wicked women, ooh, they just persist\n[00:47.92] Maybe you think it's cute, but girl, I'm not impressed\n[00:52.36] I tell you one time only with my business, please don't mess when you\n[00:57.30] Look at all these rumors, they're surrounding me everyday\n[01:01.79] I just need some time, some time to get away from\n[01:06.56] From all these rumors, I can't take it no more\n[01:10.39] My best friend said there's one out now about me and the girl next door\n[01:14.90] Did you hear that one about Tina? Some say she's much too loose\n[01:19.55] That came straight from a guy who claims he's tasted her juice\n[01:23.84] Did you hear that one about Michael? Some say he must be gay\n[01:27.84] I tried to argue, but they said if he was straight he wouldn't move that way\n[01:32.74] Did you hear that one about Susan? Some say she's just a tease\n[01:37.34] In her camisole, she's six feet tall, she'll knock you to your knees when you\n[01:42.38] Look at all these rumors, they're surrounding me everyday\n[01:46.84] I just need some time, some time to get away from\n[01:51.31] From all these rumors, I can't take it no more\n[01:55.37] My best friend said there's one out now about me and the girl next door\n[02:00.32] I can't go no place without somebody pointing a finger\n[02:04.82] I can't show my face 'cause when it comes to rumors, I'm a dead ringer\n[02:09.54] It seems from rumors I just can't get away\n[02:13.66] I bet there'll even be rumors floating around on Judgment Day\n[02:18.17] I'll think I'll write my congressman and tell him to pass a bill\n[02:22.39] For the next time they catch somebody startin' rumors, shoot to kill when you\n[02:27.58] Look at all these rumors, they're surrounding me everyday\n[02:31.93] I just need some time, some time to get away from\n[02:36.52] From all these rumors, I can't take it no more\n[02:40.68] My best friend said there's one out now about me and the girl next door\n[02:46.76] \n[03:03.08] What's mine is mine, I ain't got time for rumors in my life\n[03:07.50] I'm a man who thinks, not a man who drinks so please let me live my life\n[03:12.00] What's mine is mine, I ain't got time for rumors in my life\n[03:16.66] I'm a man who thinks, not a man who drinks so please let me live my life\n[03:21.13] What's mine is mine, I ain't got time for rumors in my life\n[03:25.66] I'm a man who thinks, not a man who drinks so please let me live my life (when you)\n[03:30.72] Look at all these rumors, they're surrounding me everyday\n[03:35.15] I just need some time, some time to get away from\n[03:40.05] From all these rumors, I can't take it no more\n[03:43.58] My best friend said there's one out now about me and the girl next door\n[03:48.77] Look at all these rumors, they're surrounding me everyday\n[03:53.16] I just need some time, some time to get away from\n[03:57.87] From all these rumors, I can't take it no more\n[04:01.86] My best friend said there's one out now about me and the girl next door\n[04:06.42] Stop (stop) spreadin' those rumors around\n[04:10.61] Stop (stop) spreadin' the lies\n[04:15.55] Stop (stop) spreadin' those rumors around\n[04:19.84] Stop (stop) spreadin' the lies\n[04:24.38] Stop (stop) spreadin' those rumors around\n[04:28.95] Stop (stop) spreadin' the lies\n[04:33.59] Stop (stop) spreadin' those rumors around\n[04:38.52] Stop (stop) spreadin' the lies\n[04:42.48] Stop (stop) spreadin' those rumors around\n[04:46.93] Stop (stop) spreadin' the lies\n[04:49.72] ",
        "composer": null,
        "publisher": null,
        "copyright": "© 1998 Del Paso Heights",
        "comment": "5A - Energy 6",
        "has_cover": true,
        "cover_format": "image/jpeg",
        "cover_size_kb": 129.17,
        "duration_seconds": 296.53,
        "bitrate": 886887,
        "sample_rate": 44100,
        "channels": 2,
        "codec": null,
        "energy_scale": "MIK"
    }
}
