{
    "file_path": "/Volumes/My Passport/Ojo otra vez musica de Tidal Original descarga/Consolidado2025/Tracks/Crazibiza, Ben Willis - No More Love (Cheesecake Boys Remix).flac",
    "timestamp": "2025-08-16T22:23:30.911982",
    "metadata": {
        "file_path": "/Volumes/My Passport/Ojo otra vez musica de Tidal Original descarga/Consolidado2025/Tracks/Crazibiza, Ben Willis - No More Love (Cheesecake Boys Remix).flac",
        "file_name": "Crazibiza, Ben Willis - No More Love (Cheesecake Boys Remix).flac",
        "file_size_mb": 33.8,
        "format": ".flac",
        "title": "No More Love (Cheesecake Boys Remix)",
        "artist": "Crazibiza, Ben Willis",
        "album": "No More Love",
        "date": "2021",
        "genre": "Tech House",
        "track_number": null,
        "album_artist": null,
        "bpm": 125.0,
        "key": "7A",
        "energy": 6.0,
        "isrc": "HUA480901143",
        "lyrics": null,
        "composer": null,
        "publisher": null,
        "copyright": null,
        "comment": "7A - Energy 6",
        "has_cover": true,
        "cover_format": "image/jpeg",
        "cover_size_kb": 47.25,
        "duration_seconds": 284.16,
        "bitrate": 995711,
        "sample_rate": 44100,
        "channels": 2,
        "codec": null,
        "energy_scale": "MIK"
    }
}
