{
    "file_path": "/Volumes/My Passport/Ojo otra vez musica de Tidal Original descarga/Consolidado2025/Tracks/Debbie Gibson - Only in My Dreams.flac",
    "timestamp": "2025-08-16T22:23:38.206665",
    "metadata": {
        "file_path": "/Volumes/My Passport/Ojo otra vez musica de Tidal Original descarga/Consolidado2025/Tracks/Debbie Gibson - Only in My Dreams.flac",
        "file_name": "Debbie Gibson - Only in My Dreams.flac",
        "file_size_mb": 26.86,
        "format": ".flac",
        "title": "Only in My Dreams",
        "artist": "Debbie Gibson",
        "album": "Greatest Hits",
        "date": "2005",
        "genre": "Synth-Pop",
        "track_number": null,
        "album_artist": null,
        "bpm": 125.0,
        "key": "5B",
        "energy": 7.0,
        "isrc": "USAT29902070",
        "lyrics": null,
        "composer": null,
        "publisher": null,
        "copyright": null,
        "comment": "5B - Energy 7",
        "has_cover": true,
        "cover_format": "image/jpeg",
        "cover_size_kb": 73.5,
        "duration_seconds": 236.53,
        "bitrate": 949568,
        "sample_rate": 44100,
        "channels": 2,
        "codec": null,
        "energy_scale": "MIK"
    }
}
