{
    "file_path": "/Volumes/My Passport/Ojo otra vez musica de Tidal Original descarga/Consolidado2025/Tracks/Def Leppard - Love Bites.flac",
    "timestamp": "2025-08-16T22:23:38.781573",
    "metadata": {
        "file_path": "/Volumes/My Passport/Ojo otra vez musica de Tidal Original descarga/Consolidado2025/Tracks/Def Leppard - Love Bites.flac",
        "file_name": "Def Leppard - Love Bites.flac",
        "file_size_mb": 42.32,
        "format": ".flac",
        "title": "Love Bites",
        "artist": "Def Leppard",
        "album": "Hysteria",
        "date": "1987",
        "genre": "Melodic Progressive Rock",
        "track_number": null,
        "album_artist": null,
        "bpm": 130.0,
        "key": "7B",
        "energy": 7.0,
        "isrc": "GBF088700608",
        "lyrics": null,
        "composer": null,
        "publisher": null,
        "copyright": null,
        "comment": "7B - Energy 7",
        "has_cover": true,
        "cover_format": "image/jpeg",
        "cover_size_kb": 168.14,
        "duration_seconds": 346.96,
        "bitrate": 1018686,
        "sample_rate": 44100,
        "channels": 2,
        "codec": null,
        "energy_scale": "MIK"
    }
}
