{
  "file_path": "/Volumes/My Passport/Ojo otra vez musica de Tidal Original descarga/Consolidado2025/Tracks/Deniece Williams - Let's Hear It for the Boy (Extended Version).flac",
  "timestamp": "2025-08-16T22:23:38.947234",
  "metadata": {
    "file_path": "/Volumes/My Passport/Ojo otra vez musica de Tidal Original descarga/Consolidado2025/Tracks/Deniece Williams - Let's Hear It for the Boy (Extended Version).flac",
    "file_name": "Deniece Williams - Let's Hear It for the Boy (Extended Version).flac",
    "file_size_mb": 42.46,
    "format": ".flac",
    "title": "Let's Hear It for the Boy (Extended Version)",
    "artist": "Deniece Williams",
    "album": "Club Columbia",
    "date": "1990",
    "genre": "Uplifting Trance 138",
    "track_number": null,
    "album_artist": null,
    "bpm": 123.0,
    "key": "8A",
    "energy": 7.0,
    "isrc": "USSM19913328",
    "lyrics": null,
    "composer": null,
    "publisher": null,
    "copyright": null,
    "comment": "8A - Energy 7",
    "has_cover": true,
    "cover_format": "image/jpeg",
    "cover_size_kb": 126.92,
    "duration_seconds": 360.93,
    "bitrate": 983332,
    "sample_rate": 44100,
    "channels": 2,
    "codec": null,
    "energy_scale": "MIK"
  }
}