{
    "file_path": "/Volumes/My Passport/Ojo otra vez musica de Tidal Original descarga/Consolidado2025/Tracks/El Cuarteto de Nos - Breve descripción de mi persona (Explicit).flac",
    "timestamp": "2025-08-16T22:23:47.722451",
    "metadata": {
        "file_path": "/Volumes/My Passport/Ojo otra vez musica de Tidal Original descarga/Consolidado2025/Tracks/El Cuarteto de Nos - Breve descripción de mi persona (Explicit).flac",
        "file_name": "El Cuarteto de Nos - Breve descripción de mi persona (Explicit).flac",
        "file_size_mb": 26.04,
        "format": ".flac",
        "title": "Breve descripción de mi persona",
        "artist": "El Cuarteto de Nos",
        "album": "Bipolar",
        "date": "2009",
        "genre": null,
        "track_number": null,
        "album_artist": null,
        "bpm": 101.0,
        "key": "10A",
        "energy": 5.0,
        "isrc": "ARF110900976",
        "lyrics": null,
        "composer": null,
        "publisher": null,
        "copyright": null,
        "comment": "10A - Energy 5",
        "has_cover": true,
        "cover_format": "image/jpeg",
        "cover_size_kb": 58.52,
        "duration_seconds": 222.24,
        "bitrate": 980243,
        "sample_rate": 44100,
        "channels": 2,
        "codec": null,
        "energy_scale": "MIK"
    }
}
