{
    "file_path": "/Volumes/My Passport/Ojo otra vez musica de Tidal Original descarga/Consolidado2025/Tracks/Fleetwood Mac - Little Lies (Extended Version) [2017 Remaster].flac",
    "timestamp": "2025-08-16T22:23:57.256227",
    "metadata": {
        "file_path": "/Volumes/My Passport/Ojo otra vez musica de Tidal Original descarga/Consolidado2025/Tracks/Fleetwood Mac - Little Lies (Extended Version) [2017 Remaster].flac",
        "file_name": "Fleetwood Mac - Little Lies (Extended Version) [2017 Remaster].flac",
        "file_size_mb": 156.92,
        "format": ".flac",
        "title": "Little Lies (Extended Version) [2017 Remaster]",
        "artist": "Fleetwood Mac",
        "album": "Tango in the Night (2017 Remaster) [Deluxe Edition]",
        "date": "1987-04-13",
        "genre": null,
        "track_number": "7",
        "album_artist": "Fleetwood Mac",
        "bpm": 125.0,
        "key": "11B",
        "energy": 7.0,
        "isrc": "USRH11603575",
        "lyrics": "[00:09.70] Tell me lies\n[00:12.98] \n[00:49.87] If I could turn the page\n[00:53.55] In time then I'd rearrange just a day or two\n[00:59.22] Close my, close my, close my eyes\n[01:05.00] But I couldn't find a way\n[01:08.75] So I'll settle for one day to believe in you\n[01:14.61] Tell me, tell me, tell me lies\n[01:19.87] Tell me lies, tell me sweet little lies\n[01:24.51] Tell me lies (tell me, tell me lies)\n[01:27.66] Oh no, no, you can't disguise\n[01:32.08] You can't disguise (no, you can't disguise)\n[01:35.19] Tell me lies, tell me sweet little lies\n[01:40.43] \n[01:43.47] Although I'm not making plans\n[01:47.20] I hope that you understand there's a reason why\n[01:53.03] Close your, close your, close your eyes\n[01:59.11] No more broken hearts\n[02:03.01] We're better off apart, let's give it a try\n[02:08.48] Tell me, tell me, tell me lies\n[02:13.70] Tell me lies, tell me sweet little lies\n[02:18.35] Tell me lies (tell me, tell me lies)\n[02:21.36] Oh no, no, you can't disguise\n[02:25.75] You can't disguise (no, you can't disguise)\n[02:29.05] Tell me lies, tell me sweet little lies\n[02:34.23] \n[02:55.68] Lie, lie, lie, lie, lies\n[03:00.34] \n[03:04.52] Tell me lies\n[03:07.75] \n[03:37.92] Tell me lies, tell me sweet little lies\n[03:42.53] Tell me lies (tell me, tell me lies)\n[03:45.68] Oh no, no, you can't disguise\n[03:50.03] You can't disguise (no, you can't disguise)\n[03:53.20] Tell me lies, tell me sweet little lies\n[03:58.30] \n[04:17.12] If I could turn the page\n[04:20.73] In time then I'd rearrange just a day or two\n[04:26.39] Close my, close my, close my eyes\n[04:32.17] But I couldn't find a way\n[04:35.85] So I'll settle for one day to believe in you\n[04:42.90] Tell me, tell me, tell me lies\n[04:46.83] Tell me lies, tell me sweet little lies\n[04:51.47] Tell me lies (tell me, tell me lies)\n[04:54.56] Oh no, no, you can't disguise\n[04:58.85] You can't disguise (no, you can't disguise)\n[05:02.13] Tell me lies, tell me sweet little lies\n[05:06.75] Tell me lies (tell me, tell me lies)\n[05:09.84] Oh no, no, you can't disguise\n[05:14.10] You can't disguise\n[05:17.38] \n[05:31.66] Tell me lies, oh, sweet little lies\n[05:37.47] Tell me lies\n[05:40.31] Oh no, no, you can't disguise\n[05:45.78] Oh-oh-oh-oh\n[05:48.95] Ooh-ooh-ooh-ooh\n[05:53.11] Sweet lies\n[05:57.03] Ooh-ooh-ooh-ooh\n[05:59.91] Sweet lies\n[06:01.57] Ooh-ooh-ooh-ooh\n[06:07.89] Little lies\n[06:09.09] ",
        "composer": null,
        "publisher": null,
        "copyright": "℗ 1987 Warner Records Inc. Remastered 2016 Rhino Entertainment",
        "comment": "11B - Energy 7",
        "has_cover": true,
        "cover_format": "image/jpeg",
        "cover_size_kb": 82.2,
        "duration_seconds": 375.52,
        "bitrate": 3500103,
        "sample_rate": 96000,
        "channels": 2,
        "codec": null,
        "energy_scale": "MIK"
    }
}
