{
    "file_path": "/Volumes/My Passport/Ojo otra vez musica de Tidal Original descarga/Consolidado2025/Tracks/Alok, Ella Eyre, Kenny Dope, Never Dull - Deep Down (feat. Never Dull) (Club Mix).flac",
    "file_name": "Alok, Ella Eyre, Kenny Dope, Never Dull - Deep Down (feat. Never Dull) (Club Mix).flac",
    "timestamp": "2025-08-16T22:41:35.183483",
    "essentia_features": {
        "loudness_lufs": -4.570276260375977,
        "danceability": 1.379196286201477,
        "acousticness": 0.5,
        "instrumentalness": 0.6863076090812683,
        "liveness": 0.1,
        "speechiness": 0.12640337423936096,
        "valence": 0.5,
        "bpm": 120.0,
        "key": "Unknown"
    },
    "format": "FLAC",
    "processing": "success"
}
