{
    "file_path": "/Volumes/My Passport/Ojo otra vez musica de Tidal Original descarga/Consolidado2025/Tracks/BANDA BLANCA - Sopa de Caracol.flac",
    "file_name": "BANDA BLANCA - Sopa de Caracol.flac",
    "timestamp": "2025-08-16T22:48:06.842473",
    "essentia_features": {
        "loudness_lufs": -6.846548080444336,
        "danceability": 1.5484628677368164,
        "acousticness": 0.5,
        "instrumentalness": 0.43974339962005615,
        "liveness": 0.1,
        "speechiness": 0.1449892188486539,
        "valence": 0.5,
        "bpm": 120.0,
        "key": "Unknown"
    },
    "format": "FLAC",
    "processing": "success"
}
