{
    "file_path": "/Volumes/My Passport/Ojo otra vez musica de Tidal Original descarga/Consolidado2025/Tracks/Beyonce\u0301 - Get Me Bodied (Extended Mix).flac",
    "file_name": "Beyonce\u0301 - Get Me Bodied (Extended Mix).flac",
    "timestamp": "2025-08-16T22:53:51.729093",
    "essentia_features": {
        "loudness_lufs": -4.976667404174805,
        "danceability": 1.4697976112365723,
        "acousticness": 0.5,
        "instrumentalness": 0.7358765006065369,
        "liveness": 0.1,
        "speechiness": 0.17774720139827663,
        "valence": 0.5,
        "bpm": 120.0,
        "key": "Unknown"
    },
    "format": "FLAC",
    "processing": "success"
}
