{
    "file_path": "/Volumes/My Passport/Ojo otra vez musica de Tidal Original descarga/Consolidado2025/Tracks/Black Box, Stepz - Strike It Up.flac",
    "file_name": "Black Box, Stepz - Strike It Up.flac",
    "timestamp": "2025-08-16T22:59:15.214904",
    "essentia_features": {
        "loudness_lufs": -5.8474884033203125,
        "danceability": 1.4917316436767578,
        "acousticness": 0.5,
        "instrumentalness": 0.5383107960224152,
        "liveness": 0.1,
        "speechiness": 0.19647028334242003,
        "valence": 0.5,
        "bpm": 120.0,
        "key": "Unknown"
    },
    "format": "FLAC",
    "processing": "success"
}
