{
  "file_path": "/Volumes/My Passport/Ojo otra vez musica de Tidal Original descarga/Consolidado2025/Tracks/Block & Crown, Soulvation, Col Jones - Bittersweet.flac",
  "file_name": "Block & Crown, Soulvation, Col Jones - Bittersweet.flac",
  "timestamp": "2025-08-16T23:13:05.925131",
  "essentia_features": {
    "loudness_lufs": -2.5130748748779297,
    "danceability": 1.2962262630462646,
    "acousticness": 0.5,
    "instrumentalness": 0.5,
    "liveness": 0.1,
    "speechiness": 0.1,
    "valence": 0.5,
    "bpm": 120.0,
    "key": "Unknown"
  },
  "format": "FLAC",
  "processing": "success"
}