{
  "file_path": "/Volumes/My Passport/Ojo otra vez musica de Tidal Original descarga/Consolidado2025/Tracks/Calle 13 - Los Idiotas.flac",
  "file_name": "Calle 13 - Los Idiotas.flac",
  "timestamp": "2025-08-16T23:22:55.841485",
  "essentia_features": {
    "loudness_lufs": -5.221185684204102,
    "danceability": 1.0680458545684814,
    "acousticness": 0.5,
    "instrumentalness": 0.4348437190055847,
    "liveness": 0.1,
    "speechiness": 0.10980112357503644,
    "valence": 0.5,
    "bpm": 120.0,
    "key": "Unknown"
  },
  "format": "FLAC",
  "processing": "success"
}