{
    "file_path": "/Volumes/My Passport/Ojo otra vez musica de Tidal Original descarga/Consolidado2025/Tracks/Cappella - U & Me (The Sound of the Future).flac",
    "file_name": "Cappella - U & Me (The Sound of the Future).flac",
    "timestamp": "2025-08-16T23:24:38.823478",
    "essentia_features": {
        "loudness_lufs": -3.756868362426758,
        "danceability": 1.5256952047348022,
        "acousticness": 0.5,
        "instrumentalness": 0.5258395373821259,
        "liveness": 0.1,
        "speechiness": 0.1983931210700862,
        "valence": 0.5,
        "bpm": 120.0,
        "key": "Unknown"
    },
    "format": "FLAC",
    "processing": "success"
}
